ctc-decoders/__init__.py
ctc-decoders/_init_paths.py
ctc-decoders/ctc_decoders.py
ctc-decoders/setup.py
ctc-decoders/swig_decoders.py
malaya_speech/__init__.py
malaya_speech/age_detection.py
malaya_speech/diarization.py
malaya_speech/emotion.py
malaya_speech/extractor.py
malaya_speech/force_alignment.py
malaya_speech/gender.py
malaya_speech/language_detection.py
malaya_speech/language_model.py
malaya_speech/multispeaker_separation.py
malaya_speech/noise_reduction.py
malaya_speech/speaker_change.py
malaya_speech/speaker_overlap.py
malaya_speech/speaker_vector.py
malaya_speech/speech_enhancement.py
malaya_speech/speechsplit_conversion.py
malaya_speech/stack.py
malaya_speech/stt.py
malaya_speech/super_resolution.py
malaya_speech/tts.py
malaya_speech/vad.py
malaya_speech/vocoder.py
malaya_speech/voice_conversion.py
malaya_speech/augmentation/__init__.py
malaya_speech/augmentation/spectrogram.py
malaya_speech/augmentation/waveform.py
malaya_speech/config/__init__.py
malaya_speech/config/cnn_rnn.py
malaya_speech/config/conformer.py
malaya_speech/config/ctc_featurizer.py
malaya_speech/config/fastspeech.py
malaya_speech/config/fastspeech2.py
malaya_speech/config/glowtts.py
malaya_speech/config/hf_wav2vec2.py
malaya_speech/config/hifigan.py
malaya_speech/config/mb_melgan.py
malaya_speech/config/melgan.py
malaya_speech/config/nuwave2.py
malaya_speech/config/speakernet_featurizer.py
malaya_speech/config/squeezeformer.py
malaya_speech/config/tacotron2.py
malaya_speech/config/transducer.py
malaya_speech/config/transducer_featurizer.py
malaya_speech/config/transformer.py
malaya_speech/config/universal_mb_melgan.py
malaya_speech/config/universal_melgan.py
malaya_speech/config/univnet.py
malaya_speech/config/vit.py
malaya_speech/config/vits.py
malaya_speech/extra/__init__.py
malaya_speech/extra/rttm.py
malaya_speech/extra/visualization.py
malaya_speech/model/__init__.py
malaya_speech/model/abstract.py
malaya_speech/model/annotation.py
malaya_speech/model/classification.py
malaya_speech-1.3.0.2.dist-info/LICENSE
malaya_speech-1.3.0.2.dist-info/METADATA
malaya_speech-1.3.0.2.dist-info/WHEEL
malaya_speech-1.3.0.2.dist-info/top_level.txt
malaya_speech-1.3.0.2.dist-info/RECORD
