Metadata-Version: 2.1
Name: malaya-speech
Version: 1.3.0.2
Summary: Speech-Toolkit for bahasa Malaysia, powered by Tensorflow and PyTorch.
Home-page: https://github.com/huseinzol05/malaya-speech
Author: huseinzol05
Author-email: husein.zol05@gmail.com
License: MIT
Download-URL: https://github.com/huseinzol05/malaya-speech/archive/master.zip
Keywords: nlp,bm
Platform: UNKNOWN
Classifier: Programming Language :: Python :: 3.6
Classifier: Intended Audience :: Developers
Classifier: License :: OSI Approved :: MIT License
Classifier: Operating System :: OS Independent
Requires-Python: >=3.6.*
Requires-Dist: dataclasses
Requires-Dist: herpetologist
Requires-Dist: librosa
Requires-Dist: malaya-boilerplate (>=0.0.23)
Requires-Dist: numpy
Requires-Dist: python-speech-features
Requires-Dist: scipy (>=1.5.4)
Requires-Dist: soundfile
Requires-Dist: torchlibrosa (==0.0.7)
Requires-Dist: tornado
Requires-Dist: tqdm
Requires-Dist: transformers
Requires-Dist: unidecode
Provides-Extra: full
Requires-Dist: pydub ; extra == 'full'
Requires-Dist: pyroomacoustics ; extra == 'full'
Requires-Dist: pysndfx ; extra == 'full'
